{
    "sourceFile": "angular.json",
    "activeCommit": 0,
    "commits": [
        {
            "activePatchIndex": 0,
            "patches": [
                {
                    "date": 1672829686820,
                    "content": "Index: \n===================================================================\n--- \n+++ \n"
                }
            ],
            "date": 1672829686820,
            "name": "Commit-0",
            "content": "{\n  \"$schema\": \"./node_modules/@angular/cli/lib/config/schema.json\",\n  \"version\": 1,\n  \"newProjectRoot\": \"projects\",\n  \"projects\": {\n    \"angular.io-example\": {\n      \"projectType\": \"application\",\n      \"root\": \"\",\n      \"sourceRoot\": \"src\",\n      \"prefix\": \"app\",\n      \"i18n\": {\n        \"sourceLocale\": \"en-US\",\n        \"locales\": {\n          \"fr\": {\n            \"translation\": \"src/locale/messages.fr.xlf\",\n            \"baseHref\": \"\"\n          }\n        }\n      },\n      \"architect\": {\n        \"build\": {\n          \"builder\": \"@angular-devkit/build-angular:browser\",\n          \"options\": {\n            \"localize\": true,\n            \"outputPath\": \"dist\",\n            \"index\": \"src/index.html\",\n            \"main\": \"src/main.ts\",\n            \"polyfills\": [\"zone.js\"],\n            \"tsConfig\": \"tsconfig.app.json\",\n            \"assets\": [\"src/favicon.ico\", \"src/assets\"],\n            \"styles\": [\"src/styles.css\"],\n            \"scripts\": [],\n            \"i18nMissingTranslation\": \"error\"\n          },\n          \"configurations\": {\n            \"production\": {\n              \"budgets\": [\n                {\n                  \"type\": \"initial\",\n                  \"maximumWarning\": \"500kb\",\n                  \"maximumError\": \"1mb\"\n                },\n                {\n                  \"type\": \"anyComponentStyle\",\n                  \"maximumWarning\": \"2kb\",\n                  \"maximumError\": \"4kb\"\n                }\n              ],\n              \"outputHashing\": \"all\"\n            },\n            \"development\": {\n              \"localize\": false,\n              \"buildOptimizer\": false,\n              \"optimization\": false,\n              \"vendorChunk\": true,\n              \"extractLicenses\": false,\n              \"sourceMap\": true,\n              \"namedChunks\": true\n            },\n            \"fr\": {\n              \"localize\": [\"fr\"],\n              \"index\": \"index-fr.html\"\n            }\n          },\n          \"defaultConfiguration\": \"production\"\n        },\n        \"serve\": {\n          \"builder\": \"@angular-devkit/build-angular:dev-server\",\n          \"configurations\": {\n            \"production\": {\n              \"browserTarget\": \"angular.io-example:build:production\"\n            },\n            \"development\": {\n              \"browserTarget\": \"angular.io-example:build:development\"\n            },\n            \"fr\": {\n              \"browserTarget\": \"angular.io-example:build:development,fr\"\n            }\n          },\n          \"defaultConfiguration\": \"development\"\n        },\n        \"extract-i18n\": {\n          \"builder\": \"@angular-devkit/build-angular:extract-i18n\",\n          \"options\": {\n            \"browserTarget\": \"angular.io-example:build\"\n          }\n        },\n        \"test\": {\n          \"builder\": \"@angular-devkit/build-angular:karma\",\n          \"options\": {\n            \"polyfills\": [\"zone.js\", \"zone.js/testing\"],\n            \"tsConfig\": \"tsconfig.spec.json\",\n            \"assets\": [\"src/favicon.ico\", \"src/assets\"],\n            \"styles\": [\"src/styles.css\"],\n            \"scripts\": []\n          }\n        },\n        \"e2e\": {\n          \"builder\": \"@angular-devkit/build-angular:protractor\",\n          \"options\": {\n            \"protractorConfig\": \"e2e/protractor.conf.js\",\n            \"devServerTarget\": \"angular.io-example:serve:fr\"\n          },\n          \"configurations\": {\n            \"production\": {\n              \"devServerTarget\": \"angular.io-example:serve:production\"\n            }\n          }\n        }\n      }\n    }\n  },\n  \"cli\": {\n    \"analytics\": \"b7a65a30-63e3-4cfa-9412-704a37b64e50\"\n  }\n}\n"
        }
    ]
}